pythonBgt/__init__.py
pythonBgt/pythonBgt.py
pythonBgt-0.49.1.dist-info/METADATA
pythonBgt-0.49.1.dist-info/WHEEL
pythonBgt-0.49.1.dist-info/top_level.txt
pythonBgt-0.49.1.dist-info/RECORD
