Metadata-Version: 2.1
Name: pythonBgt
Version: 0.49.1
Summary: PythonBgt is a library for Python that allows the easy and practical creation of audiogames, combining the flexibility and modernity of Python with the simplicity and practicality of BGT.
Author: Gabriel Haberkamp
Keywords: Python,BGT,Python_Bgt,audiogame,audiogames,games
Requires-Dist: pygame
Requires-Dist: sound-lib
Requires-Dist: wxpython
Requires-Dist: requests
Requires-Dist: accessible-output2
Requires-Dist: pyperclip
Requires-Dist: pyenet311
